README.md
setup.py
aspose3dcloud/__init__.py
aspose3dcloud/api_client.py
aspose3dcloud/configuration.py
aspose3dcloud/rest.py
aspose3dcloud.egg-info/PKG-INFO
aspose3dcloud.egg-info/SOURCES.txt
aspose3dcloud.egg-info/dependency_links.txt
aspose3dcloud.egg-info/requires.txt
aspose3dcloud.egg-info/top_level.txt
aspose3dcloud/apis/__init__.py
aspose3dcloud/apis/o_auth_api.py
aspose3dcloud/apis/three_d_cloud_api.py
aspose3dcloud/models/__init__.py
aspose3dcloud/models/access_token_response.py
aspose3dcloud/models/amf_save_option.py
aspose3dcloud/models/box.py
aspose3dcloud/models/collada_save_option.py
aspose3dcloud/models/collada_transform_style.py
aspose3dcloud/models/cylinder.py
aspose3dcloud/models/disc_usage.py
aspose3dcloud/models/discreet3_ds_save_option.py
aspose3dcloud/models/draco_compression_level.py
aspose3dcloud/models/draco_save_option.py
aspose3dcloud/models/entity.py
aspose3dcloud/models/error.py
aspose3dcloud/models/error_details.py
aspose3dcloud/models/fbx_save_option.py
aspose3dcloud/models/file_content_type.py
aspose3dcloud/models/file_version.py
aspose3dcloud/models/file_versions.py
aspose3dcloud/models/files_list.py
aspose3dcloud/models/files_upload_result.py
aspose3dcloud/models/gltf_save_option.py
aspose3dcloud/models/html_save_option.py
aspose3dcloud/models/model_data.py
aspose3dcloud/models/obj_save_option.py
aspose3dcloud/models/object_exist.py
aspose3dcloud/models/pdf_lighting_scheme.py
aspose3dcloud/models/pdf_render_mode.py
aspose3dcloud/models/pdf_save_option.py
aspose3dcloud/models/plane.py
aspose3dcloud/models/ply_save_option.py
aspose3dcloud/models/rvm_save_option.py
aspose3dcloud/models/save_format.py
aspose3dcloud/models/save_options.py
aspose3dcloud/models/sphere.py
aspose3dcloud/models/stl_save_option.py
aspose3dcloud/models/storage_exist.py
aspose3dcloud/models/storage_file.py
aspose3dcloud/models/torus.py
aspose3dcloud/models/transform.py
aspose3dcloud/models/u3_d_save_option.py
aspose3dcloud/models/vector3.py
test/test_base.py
test/test_three_d_cloud_api.py